{
  "version": "vary-sim-v1",
  "exported": "2026-04-01T13:31:05.136Z",
  "sliders": {
    "pvPeak": 50,
    "irrPeak": 1000,
    "solarNoon": 12,
    "sunrise": 6,
    "sunset": 18,
    "convEff": 90,
    "batV": 12,
    "batAh": 10,
    "initSoc": 50,
    "maxDis": 100,
    "maxCharge": 40,
    "minSoc": 20,
    "cookPow": 70,
    "waterTemp": 25,
    "heatLoss": 25
  },
  "sessions": [
    {
      "start": 6,
      "end": 7,
      "power": 70,
      "boost": false
    },
    {
      "start": 11,
      "end": 12,
      "power": 70,
      "boost": true
    },
    {
      "start": 18,
      "end": 19,
      "power": 60,
      "boost": false
    }
  ]
}